django_inscode/__init__.py
django_inscode/apps.py
django_inscode/authentication.py
django_inscode/exceptions.py
django_inscode/middlewares.py
django_inscode/mixins.py
django_inscode/models.py
django_inscode/permissions.py
django_inscode/repositories.py
django_inscode/serializers.py
django_inscode/services.py
django_inscode/settings.py
django_inscode/transports.py
django_inscode/views.py
django_inscode/utils/__init__.py
django_inscode/utils/date.py
django_inscode/utils/decimal.py
django_inscode-1.7.7.dist-info/METADATA
django_inscode-1.7.7.dist-info/WHEEL
django_inscode-1.7.7.dist-info/top_level.txt
django_inscode-1.7.7.dist-info/RECORD
