Metadata-Version: 2.4
Name: django-inscode
Version: 1.7.7
Summary: Django framework da Inscode.
Classifier: Framework :: Django
Classifier: Programming Language :: Python :: 3
Classifier: License :: OSI Approved :: MIT License
Classifier: Operating System :: OS Independent
Requires-Python: >=3.12
Requires-Dist: Django>=5.1
Requires-Dist: django-soft-delete>=1.0.16
Requires-Dist: pytz>=2024.2
Requires-Dist: marshmallow>=3.26.0
Requires-Dist: django-filter>=24.3
Requires-Dist: mozilla-django-oidc>=4.0.1
Dynamic: classifier
Dynamic: description
Dynamic: description-content-type
Dynamic: requires-dist
Dynamic: requires-python
Dynamic: summary
